fvalue/__init__.py
fvalue/fvalue.py
fvalue-1.0.0.dist-info/LICENSE.md
fvalue-1.0.0.dist-info/METADATA
fvalue-1.0.0.dist-info/WHEEL
fvalue-1.0.0.dist-info/top_level.txt
fvalue-1.0.0.dist-info/RECORD
