Metadata-Version: 2.1
Name: fvalue
Version: 1.0.0
Summary: Values and their uncertainties formatter up to a given number of significant figures in the uncertainty.
Home-page: https://github.com/MartyO256/py-formatted-value
Author: Marc-Antoine Ouimet
Author-email: ouimetmarcantoine@gmail.com
License: UNKNOWN
Keywords: significant figures values uncertainty formatting format
Platform: UNKNOWN
Classifier: Intended Audience :: Science/Research
Classifier: License :: OSI Approved :: MIT License
Classifier: Programming Language :: Python :: 3
